sboon_ai_dev/__init__.py
sboon_ai_dev/datasets/__init__.py
sboon_ai_dev/datasets/loader.py
sboon_ai_dev/datasets/data/data_energy.csv
sboon_ai_dev/datasets/data/sample_data.csv
sboon_ai_dev/h5_manager/__init__.py
sboon_ai_dev/h5_manager/core.py
sboon_ai_dev-0.1.0.dist-info/licenses/LICENSE
sboon_ai_dev-0.1.0.dist-info/METADATA
sboon_ai_dev-0.1.0.dist-info/WHEEL
sboon_ai_dev-0.1.0.dist-info/top_level.txt
sboon_ai_dev-0.1.0.dist-info/RECORD
