Metadata-Version: 2.4
Name: sboon_ai_dev
Version: 0.1.0
Summary: SbooN Logic & AI Studio : Tools Library [PyPi]
Author: BOONNATEE SAKBOONYARAT
Author-email: boonnatee@gmail.com, boonnatee.sak@mwit.ac.th
License: MIT License
Project-URL: Homepage, https://git.mwit.ac.th/cs/sboon-tool-library
Project-URL: Bug Tracker, https://git.mwit.ac.th/groups/cs/sboon-tool-library/-/boards
Requires-Python: >=3.10
License-File: LICENSE
Requires-Dist: h5py
Requires-Dist: matplotlib
Requires-Dist: numpy
Requires-Dist: pandas
Requires-Dist: requests
Dynamic: license-file
